cpu_power/__init__.py
cpu_power.py-0.1.1.data/scripts/cpu-power
cpu_power.py-0.1.1.dist-info/LICENSE
cpu_power.py-0.1.1.dist-info/METADATA
cpu_power.py-0.1.1.dist-info/WHEEL
cpu_power.py-0.1.1.dist-info/top_level.txt
cpu_power.py-0.1.1.dist-info/RECORD
