Metadata-Version: 2.1
Name: cpu-power.py
Version: 0.1.1
Summary: Set Linux CPU power settings
Home-page: https://github.com/six-two/cpu-power.py
Author: six-two
Author-email: pip@six-two.dev
License: MIT License
Platform: UNKNOWN
Classifier: License :: OSI Approved :: MIT License
Classifier: Operating System :: POSIX :: Linux
Classifier: Programming Language :: Python :: 3
Classifier: Programming Language :: Python :: 3.9
Classifier: Programming Language :: Python :: 3.10
Requires-Python: >=3.9
License-File: LICENSE
